mux.v
module mux_2_1(TXOut,TXbuff0, TXbuff1, passTXbuff);

input TXbuff0,TXbuff1;
input passTXbuff;


output reg TXOut;

always @(passTXbuff) begin
if(~passTXbuff)
assign TXOut=TXbuff0;

if (passTXbuff)
   assign TXOut=TXbuff1;
end
endmodule

shiftregister.v
module txData(dataOut,shift,load,dataIn,clk);

output reg dataOut;
output TXBuff0;
input shift,load,clk;
input [31:0] dIn;
reg [31:0] buffer;

output [31:0] dataIn;
assign dataIn=dIn;


initial begin
buffer=31'b0;
end

always @(posedge clk,dataIn)
	begin
		if(load)
		buffer <= dataIn;

		else if(shift)
			begin
				dataOut <= buffer[0];
				buffer <= buffer>>1;
			end
		else
			buffer <= buffer;
	end

assign TXBuff0 = dataOut;

endmodule

dp_components.v
module txDataPath(StartTX,TXIn,ShiftTXBuff0,ShiftTXBuff1,LoadTXBuff0,LoadTXBuff1,dataIn,TXBuff0,TXBuff1,clk,TXOut,passTXbuff);

input [31:0] TXIn;
input StartTX,ShiftTXBuff0,ShiftTXBuff1,LoadTXBuff0,LoadTXBuff1,passTXbuff,clk;
output [31:0] dataIn;
output TXBuff0,TXBuff1,TXOut;
assign dataIn=TXIn;




output loadbuffer0,loadbuffer1,shiftbuffer0,shiftbuffer1;



and(loadbuffer0,StartTX ,LoadTXBuff0);
and(loadbuffer1,StartTX,LoadTXBuff1);
and(shiftbuffer0,StartTX,ShiftTXBuff0);
and(shiftbuffer1,StartTX,ShiftTXBuff1);

txData buff0(.clk(clk),.load(loadbuffer0),.shift(shiftbuffer0),.dataIn(dataIn),.dataOut(TXBuff0));
txData buff1(.clk(clk),.load(loadbuffer1),.shift(shiftbuffer1),.dataIn(dataIn),.dataOut(TXBuff1));
mux_2_1 mux(.TXOut(TXOut),.TXbuff0(TXBuff0), .TXbuff1(TXBuff1),.passTXbuff(passTXbuff));

endmodule

BurstCounter (1).v
module burstcounter(reset,inc,cnt);
input reset, inc;
output reg [5:0] cnt;

always @ (inc or reset) begin

if(reset) 
cnt = 1'd0;
else begin
if(inc) begin
cnt <= cnt+1'd1;
end
end
end
endmodule

upcounter.v
module TXcounter(reset,inc,cnt,clk);
input reset, inc, clk;
output reg [5:0] cnt;

always @ (posedge clk)
begin
    if(reset)
        cnt = 1'd1;
    else
        begin
        if(inc)
        cnt <= cnt+1'd1;
        end
end
endmodule

TXController (2).v
//`timescale 10ns/1ns
module txcontroller(clk, StartTX,Ackrecvd,TXCount,BurstCnt, ResetTXCount, IncTXCount, LoadTXBuf0, LoadTXBuf1, ShiftTXBuf0, ShiftTXBuf1, PassTXBuf ,SendStartSig, SendWriteSig, SendStopSig,WaitAck,LoadAddr, SDA, SCL, ResetBurstCnt, IncBurstCnt);

input StartTX, clk;
input [5:0] TXCount;
input [5:0] BurstCnt;
input  SDA, SCL;
output reg ResetTXCount, IncTXCount, LoadTXBuf0, LoadTXBuf1, ShiftTXBuf0, ShiftTXBuf1, PassTXBuf, LoadAddr ,SendStartSig, SendWriteSig, WaitAck, ResetBurstCnt, IncBurstCnt, SendStopSig;
input Ackrecvd;

reg [3:0] PS;
reg [3:0] NS;
reg [5:0] Count; //
parameter size = 6'b001111;
parameter burst = 6'b00010;
parameter IDLE  = 4'b0001, LOADADDRB0 = 4'b0010,PRELOADB1 = 4'b0011 , SENDADDR = 4'b0100, SENDWRITE = 4'b0101, 
         WAITACK = 4'b0110, LOADB0 = 4'b0111, EMPTYB1 = 4'b1000 , WAITACK1 = 4'b1001, LOADB1 = 4'b1010, EMPTYB0 = 4'b1011, WAITACK0= 4'b1100, SENDSTOP = 4'b1101 ; 
initial begin
PS <= IDLE;
NS <= LOADADDRB0;
LoadTXBuf0 <= 1'b0;
LoadTXBuf1 <= 1'b0;
ShiftTXBuf0 <= 1'b0;
ShiftTXBuf1 <= 1'b0;
ResetTXCount <= 1'b0;
IncTXCount <= 1'b0;
PassTXBuf <= 1'b0;
SendStartSig <= 1'b0;
SendWriteSig <= 1'b0;
WaitAck <= 1'b0;
ResetBurstCnt <= 1'b0;
IncBurstCnt <= 1'b0; 
SendStopSig <= 1'b0;
LoadAddr <= 1'b0;
end

always @ (posedge clk) begin
PS = NS;

if(StartTX==0) begin
NS <= IDLE;
end 
else begin

case(PS) 

IDLE    :    begin
             NS <= LOADADDRB0;
             end

LOADADDRB0: begin
           LoadTXBuf0 <= 1'b1;
           LoadAddr <= 1'b1;
           Count <= 6'b000111;
           ResetTXCount <= 1'b1;
	       SendStartSig <= 1'b1;
           NS <= PRELOADB1;
           end

PRELOADB1: begin
        LoadAddr <= 1'b0;
        ResetTXCount <= 1'b0;
        SendStartSig <= 1'b0;
        LoadTXBuf0 <= 1'b0;
     	LoadTXBuf1 <= 1'b1;
        ShiftTXBuf0 <= 1'b1;
        ShiftTXBuf1 <= 1'b0;
        IncTXCount <= 1'b1;
        PassTXBuf <= 1'b0;
        NS <= SENDADDR;
        end

SENDADDR: begin
         if(TXCount < Count-1) begin
         LoadTXBuf1 <= 1'b0;
         ShiftTXBuf0 <= 1'b1;
         IncTXCount <= 1'b1;
         end
         if(TXCount == Count-1) begin
         NS <= SENDWRITE;

         end
         end

SENDWRITE : begin
            ShiftTXBuf0 <= 1'b0;
            SendWriteSig <= 1'b1;
            IncTXCount <= 1'b0;
            NS <= WAITACK;
            end

WAITACK: begin 
         SendWriteSig <= 1'b0;
         WaitAck <= 1'b1;
         Count = 4'b1000;
         ResetTXCount <= 1'b1;
         ResetBurstCnt <= 1'b1;
         if(Ackrecvd == 1'b1) begin
         NS <= LOADB0;
         end
         end
         
LOADB0: begin                       //load buffer 0 and shift buffer 1
        WaitAck <= 1'b0;
        ResetTXCount <= 1'b0;
        ResetBurstCnt <= 1'b0;
        LoadTXBuf0 <= 1'b1;
        ShiftTXBuf1 <= 1'b1;
        IncTXCount <= 1'b1;
        PassTXBuf <= 1'b1;
        NS <= EMPTYB1;
        end
EMPTYB1: begin
         if(TXCount <= Count) begin
         if((TXCount % 6'b001000) == 0) begin
         IncTXCount <= 1'b0;
         NS <= WAITACK1;
         end
         else begin
         LoadTXBuf1 <= 1'b0;
         ShiftTXBuf0 <= 1'b1;
         PassTXBuf <= 1'b0;
         IncTXCount <= 1'b1;
         end
         end else begin
         IncBurstCnt <= 1'b1;
         NS <= WAITACK1;
         end
         end
        
WAITACK1: begin
         WaitAck <= 1'b1;
         if(SDA== 1'b0) begin
         if((TXCount > Count)&&(BurstCnt < burst)) begin
         Count = size ;
         ResetTXCount <= 1'b1;
         NS <= LOADB1;
         end else if((TXCount <= Count)&&(BurstCnt < burst)) begin
         NS <= EMPTYB1;
         end else if(BurstCnt == burst)begin
         NS <= SENDSTOP; 
         end
         end
         end
LOADB1: begin
        IncBurstCnt <= 1'b0;
        IncBurstCnt <= 1'b0;
        ResetTXCount <= 1'b0;
        LoadTXBuf0 <= 1'b0;
     	LoadTXBuf1 <= 1'b1;
        ShiftTXBuf0 <= 1'b1;
        ShiftTXBuf1 <= 1'b0;
        IncTXCount <= 1'b1;
        PassTXBuf <= 1'b0;
        NS <= EMPTYB0;
        end
EMPTYB0: begin
         if(TXCount <= Count) begin
         if((TXCount % 6'b001000) == 0)begin
         IncTXCount <= 1'b0;
         NS <= WAITACK0;
         end else begin
         LoadTXBuf1 <= 1'b0;
         ShiftTXBuf0 <= 1'b1;
         PassTXBuf <= 1'b0;
         IncTXCount <= 1'b1;
         end
         end
         else begin
         IncBurstCnt <= 1'b1;
         NS <= WAITACK0;
         end
         end
        

WAITACK0: begin
         WaitAck <= 1'b1;
         if(SDA== 1'b0) begin
         if((TXCount > Count)&&(BurstCnt < burst)) begin
         Count = size ;
         ResetTXCount <= 1'b1;
         NS <= LOADB0;
         end else if((TXCount <= Count)&&(BurstCnt < burst)) begin
         NS <= EMPTYB0;
         end else if(BurstCnt == burst) begin
         NS <= SENDSTOP; 
         end
         end
         end
SENDSTOP: begin
          SendStopSig <= 1'b1;
          NS<= IDLE;
          end
        
         
default: NS <= IDLE;
      

endcase


end

end

TXcounter m1(ResetTXCount,IncTXCount,TXCount,clk);
burstcounter m2(ResetBurstCnt, IncBurstCnt, BurstCnt);
endmodule

contRegs_components.v
module controlReg(dataOut,write,dataIn,clk);
output reg[31:0] dataOut;
input write,clk;
input[31:0] dataIn;
reg [31:0] ctrlReg;


always@(posedge clk) begin
if(write==1) begin
ctrlReg = dataIn;
dataOut = ctrlReg;
end
else begin
ctrlReg = ctrlReg;
dataOut = ctrlReg;
end
end
endmodule


module deMux(inBurst,inSize,addr,write);
output reg inBurst;
output reg inSize;
input write;
input [3:0] addr;

always @ (write,addr)
begin
    if(addr[0]==0) begin
        assign inBurst = write;
        assign inSize = 0;
        end
    else if(addr[0]) begin
        assign inSize = write;
        assign inBurst = 0;
        end
end  
endmodule

contRegs_dp.v
module dataPath(clk,size,dataIn,addr,write,brst);

input write,clk;
input [31:0] dataIn;
input [3:0] addr;
//output [31:0] size;
output [31:0] brst,size;
wire inSize,inBurst;

controlReg  burst(brst,inBurst,dataIn,clk);
controlReg datasize(size,inSize,dataIn,clk);
deMux demux(inBurst,inSize,addr,write);

endmodule


//module controlReg(dataOut,write,dataIn,clk);

masterTx.v
module master (clk, StartTX,TXIn,TXout,write,addr,TXBuff0,TXBuff1);

// Declaring inputs and outputs of the whole master transmission block, these are driven by the testbench

input wire clk,StartTX,write;
input wire [31:0] TXIn;
wire [31:0] dataIn;
input [3:0] addr;
output TXout;
output TXBuff0,TXBuff1;

/*Declaring wire's the interconnect the components of the transmission block
TX controlregister unit output to the inputs of the controller brst --> burst upcounter's cnt */

wire [31:0] burst, size;


initial begin
$dumpfile("dump1.vcd");
$dumpvars(1);
end

// Declaring inputs and outputs of the state machine block

input wire[5:0] TXCount,BurstCnt; //wire that goes from the counter outputs  to the finite State Machine inputs

wire ResetTXCount, IncTXCount, LoadTXBuff0, LoadTXBuff1, ShiftTXBuff0, ShiftTXBuff1,
passTXbuff,SendStartSig, SendWriteSig, SendStopSig,WaitAck,LoadAddr,SDA,SCL,ResetBurstCnt, IncBurstCnt,Ackrecvd;



// Declaring inputs and outputs of the double buffered transmitter
//output reg[31:0] dataIn;


/***************************************************************************************
--------------- TRANSMITTER CONTROL REGISTER FOR SIZE AND BURST----------------

To write to the registers, the test-bench needs to address them and write data to
them by asserting the Write signal and putting the data on the dedicated data bus
provided to program them. There is a 4 bit address space available and you can choose
 to assign any address to these two registers.
*******************************************************************************/

dataPath cRegsdp(.clk(clk),.size(size),.dataIn(dataIn),.addr(addr),.write(write),.brst(burst));




/***********************************************************************************************************
--------------- TRANSMITTER CONTROLLER FOR DOUBLE BUFFERED TRANSMISSION AND I2C INTERFACE----------------

Once the registers are programmed, the test-bench will assert the StartTx control signal which
starts the control state machine and the transmission operation
************************************************************************************************************/

txcontroller controllerUnit(.clk(clk),.StartTX(StartTX),.Ackrecvd(Ackrecvd),.TXCount(TXCount),.BurstCnt(BurstCnt), .ResetTXCount(ResetTXCount), .IncTXCount(IncTXCount),
.LoadTXBuf0(LoadTXBuff0), .LoadTXBuf1(LoadTXBuff1),.ShiftTXBuf0(ShiftTXBuff0), .ShiftTXBuf1(ShiftTXBuff1), .PassTXBuf(passTXbuff) ,.SendStartSig(SendStartSig),
.SendWriteSig(SendWriteSig),.SendStopSig(SendStopSig),.WaitAck(WaitAck),.LoadAddr(LoadAddr), .SDA(SDA), .SCL(SCL), .ResetBurstCnt(ResetBurstCnt), .IncBurstCnt(IncBurstCnt));


/***********************************************************************************************************
---------------DOUBLE BUFFERED TRANSMISSION----------------
Each time the Tx unit needs the next set of data, it will assert the ReadyData signal to the testbench.
The test-bench should respond to this signal by providing the next data chunk to transmit
(based on the size programmed in the control register) to the Tx unit on the dedicated TxData
bus.
************************************************************************************************************/

txDataPath datapath(.clk(clk),.StartTX(StartTX),.TXIn(TXIn),.ShiftTXBuff0(ShiftTXBuff0),.ShiftTXBuff1(ShiftTXBuff1),.LoadTXBuff0(LoadTXBuff0),
.LoadTXBuff1(LoadTXBuff1),.dataIn(dataIn),.TXBuff0(TXBuff0),.TXBuff1(TXBuff1),.TXOut(TXout),.passTXbuff(passTXbuff));


endmodule

testbench.v
module testbench;

output TXout;
output TXBuff0,TXBuff1;

reg clk,StartTX,write;
//output [31:0] dataIn;
reg [3:0] addr;
reg [31:0] TXIn;

master m1 (.clk(clk),.StartTX(StartTX),.TXIn(TXIn),.TXout(TXout),.write(write),.addr(addr),.TXBuff0(TXBuff0),.TXBuff1(TXBuff1));

initial begin
$dumpfile("dump.vcd");
$dumpvars(1);
clk=1'b1;
StartTX=0;
write = 0;
end

always #10 clk=~clk;
initial begin
StartTX=0;
addr=4'b0000;
TXIn=32'd2;

#10 write=1;

// *************** #50 addr = 4'b0001; TXIn=32'd64; write = 0; *************** //

#50 addr = 4'b0001; TXIn=32'd8; write = 1;

#50 StartTX=1; TXIn=32'd67;

end
initial
#1000 $stop;
endmodule

datapathTb.v
module test;
reg clk,ShiftTXBuff0,ShiftTXBuff1,LoadTXBuff0,LoadTXBuff1,StartTX,passTXbuff;
reg [31:0] TXIn;
reg [31:0] buffer;
output[31:0] dataIn;
output TXBuff0,TXBuff1,TXOut;


txDataPath datapath(.clk(clk),.StartTX(StartTX),.TXIn(TXIn),.ShiftTXBuff0(ShiftTXBuff0),.ShiftTXBuff1(ShiftTXBuff1),.LoadTXBuff0(LoadTXBuff0),.LoadTXBuff1(LoadTXBuff1),.dataIn(dataIn),.TXBuff0(TXBuff0),.TXBuff1(TXBuff1),.TXOut(TXOut),.passTXbuff(passTXbuff));

initial begin
$dumpfile("dump.vcd");
$dumpvars(1);
clk=1'b1;
StartTX=1;
end

always #10 clk=~clk;
initial begin
LoadTXBuff0=1'b1;
LoadTXBuff1=1'b0;
ShiftTXBuff0=1'b0;
ShiftTXBuff1=1'b0;
TXIn=32'd67;
passTXbuff=0;
#100 ShiftTXBuff0=1'b1; LoadTXBuff0=1'b0;


# 200 ShiftTXBuff0=1'b0; LoadTXBuff0=1'b0;
#100 LoadTXBuff1=1'b1;
#300 ShiftTXBuff1=1'b1; LoadTXBuff1=1'b0; passTXbuff=1;



end
initial
#1000 $stop;
endmodule

fsmtb.v
module fsmtb;

reg clk, StartTX,Ackrecvd;
input [5:0] TXCount;
input [5:0] BurstCnt;
output ResetTXCount, IncTXCount, LoadTXBuff0, LoadTXBuff1, ShiftTXBuff0, ShiftTXBuff1, passTXbuff ,SendStartSig, SendWriteSig, SendStopSig,WaitAck,LoadAddr, ResetBurstCnt, IncBurstCnt;

txcontroller controllerUnit(.clk(clk),.StartTX(StartTX),.Ackrecvd(Ackrecvd),.TXCount(TXCount),.BurstCnt(BurstCnt), .ResetTXCount(ResetTXCount), .IncTXCount(IncTXCount),
.LoadTXBuf0(LoadTXBuff0), .LoadTXBuf1(LoadTXBuff1),.ShiftTXBuf0(ShiftTXBuff0), .ShiftTXBuf1(ShiftTXBuff1), .PassTXBuf(passTXbuff) ,.SendStartSig(SendStartSig),
.SendWriteSig(SendWriteSig),.SendStopSig(SendStopSig),.WaitAck(WaitAck),.LoadAddr(LoadAddr), .SDA(SDA), .SCL(SCL), .ResetBurstCnt(ResetBurstCnt), .IncBurstCnt(IncBurstCnt));






initial begin
$dumpfile("dump.vcd");
$dumpvars(1);
clk=1'b1;
StartTX=0;
end

always #10 clk=~clk;
initial begin


#50 StartTX=1; 

end
initial
#1000 $stop;
endmodule

dump.vcd
$date
	Tue May  9 21:23:53 2017
$end
$version
	Icarus Verilog
$end
$timescale
	1s
$end
$scope module fsmtb $end
$var wire 1 ! SCL $end
$var wire 1 " SDA $end
$var wire 1 # passTXbuff $end
$var wire 1 $ WaitAck $end
$var wire 6 % TXCount [5:0] $end
$var wire 1 & ShiftTXBuff1 $end
$var wire 1 ' ShiftTXBuff0 $end
$var wire 1 ( SendWriteSig $end
$var wire 1 ) SendStopSig $end
$var wire 1 * SendStartSig $end
$var wire 1 + ResetTXCount $end
$var wire 1 , ResetBurstCnt $end
$var wire 1 - LoadTXBuff1 $end
$var wire 1 . LoadTXBuff0 $end
$var wire 1 / LoadAddr $end
$var wire 1 0 IncTXCount $end
$var wire 1 1 IncBurstCnt $end
$var wire 6 2 BurstCnt [5:0] $end
$var reg 1 3 Ackrecvd $end
$var reg 1 4 StartTX $end
$var reg 1 5 clk $end
$upscope $end
$scope module test $end
$var wire 32 6 dataIn [31:0] $end
$var wire 1 7 TXOut $end
$var wire 1 8 TXBuff1 $end
$var wire 1 9 TXBuff0 $end
$var reg 1 : LoadTXBuff0 $end
$var reg 1 ; LoadTXBuff1 $end
$var reg 1 < ShiftTXBuff0 $end
$var reg 1 = ShiftTXBuff1 $end
$var reg 1 > StartTX $end
$var reg 32 ? TXIn [31:0] $end
$var reg 1 @ clk $end
$var reg 1 A passTXbuff $end
$upscope $end
$scope module testbench $end
$var wire 1 B TXout $end
$var wire 1 C TXBuff1 $end
$var wire 1 D TXBuff0 $end
$var reg 1 E StartTX $end
$var reg 32 F TXIn [31:0] $end
$var reg 4 G addr [3:0] $end
$var reg 1 H clk $end
$var reg 1 I write $end
$upscope $end
$scope module fsmtb $end
$upscope $end
$scope module test $end
$upscope $end
$scope module testbench $end
$upscope $end
$scope module fsmtb $end
$upscope $end
$scope module test $end
$upscope $end
$scope module testbench $end
$upscope $end
$scope module fsmtb $end
$upscope $end
$scope module test $end
$upscope $end
$scope module testbench $end
$upscope $end
$enddefinitions $end
#0
$dumpvars
0I
1H
b0 G
b10 F
0E
xD
xC
xB
0A
1@
b1000011 ?
1>
0=
0<
0;
1:
x9
x8
x7
b1000011 6
15
04
x3
bx 2
01
00
0/
0.
0-
0,
0+
0*
0)
0(
0'
0&
bx %
0$
0#
z"
z!
$end
#10
1I
0H
0@
05
#20
1H
1@
15
#30
0H
0@
05
#40
1H
1@
15
#50
0H
0@
05
14
#60
1H
1@
15
b1000 F
b1 G
#70
0H
0@
05
#80
1*
1+
1/
1.
1H
1@
15
#90
0H
0@
05
#100
17
19
10
1'
1-
0.
0*
0+
0/
b1 %
1H
1@
15
0:
1<
#110
0H
0@
05
b1000011 F
1E
#120
b10 %
0-
1H
1@
15
#130
0H
0@
05
#140
07
09
b11 %
1H
1@
15
#150
0H
0@
05
#160
b100 %
1H
1@
15
#170
0H
0@
05
#180
1B
1D
b101 %
1H
1@
15
#190
0H
0@
05
#200
b110 %
1H
1@
15
#210
0H
0@
05
#220
0B
0D
17
19
b111 %
1H
1@
15
#230
0H
0@
05
#240
07
09
b1000 %
00
1(
0'
1H
1@
15
#250
0H
0@
05
#260
b0 2
1,
1+
1$
0(
1H
1@
15
#270
0H
0@
05
#280
b1 %
1H
1@
15
#290
0H
0@
05
#300
1B
1D
1H
1@
15
0<
#310
0H
0@
05
#320
1H
1@
15
#330
0H
0@
05
#340
1H
1@
15
#350
0H
0@
05
#360
1H
1@
15
#370
0H
0@
05
#380
1H
1@
15
#390
0H
0@
05
#400
1H
1@
15
1;
#410
0H
0@
05
#420
1H
1@
15
#430
0H
0@
05
#440
1H
1@
15
#450
0H
0@
05
#460
1H
1@
15
#470
0H
0@
05
#480
1H
1@
15
#490
0H
0@
05
#500
1H
1@
15
#510
0H
0@
05
#520
1H
1@
15
#530
0H
0@
05
#540
1H
1@
15
#550
0H
0@
05
#560
1H
1@
15
#570
0H
0@
05
#580
1H
1@
15
#590
0H
0@
05
#600
1H
1@
15
#610
0H
0@
05
#620
1H
1@
15
#630
0H
0@
05
#640
1H
1@
15
#650
0H
0@
05
#660
1H
1@
15
#670
0H
0@
05
#680
1H
1@
15
#690
0H
0@
05
#700
18
17
1H
1@
15
1A
0;
1=
#710
0H
0@
05
#720
1H
1@
15
#730
0H
0@
05
#740
07
08
1H
1@
15
#750
0H
0@
05
#760
1H
1@
15
#770
0H
0@
05
#780
1H
1@
15
#790
0H
0@
05
#800
1H
1@
15
#810
0H
0@
05
#820
17
18
1H
1@
15
#830
0H
0@
05
#840
07
08
1H
1@
15
